[
    {
        "type": "checkbox",
        "title": "Что включает в себя инженерно-техническая подготовка производства?Выберите все правильные ответы.",
        "image": null,
        "component": "/templates_4/questions/question_1/slide_1.html",
        "answers": [ "A", "E"]
    },
    {
        "type": "checkbox",
        "title": "На какие виды делится техническая подготовка в зависимости от планирования сроков выполнения?.",
        "image": null,
        "component": "/templates_4/questions/question_1/slide_2.html",
        "answers": [ "C", "E" ]
    },
    {
        "type": "checkbox",
        "title": "Какие обязательные разделы содержит техническое задание на создание (развитие или модернизацию) автоматизированной системы?Выберите все правильные ответы.",
        "image": null,
        "component": "/templates_4/questions/question_1/slide_3.html",
        "answers": ["A", "C", "F"]
    },
    {
        "type": "checkbox",
        "title": "Что можно определить прочитав функциональную схему автоматизации? Выберите все правильные ответы.",
        "image": null,
        "component":"/templates_4/questions/question_1/slide_4.html",
        "answers": ["A", "B", "C", "D", "E", "F"]
    },
    {
        "type": "select",
        "title": "Приведите в соответствие наименование и обозначение ГОСТов",
        "image": null,
        "component":"/templates_4/questions/question_1/slide_5.html",
        "answers": ["2", "1", "4", "6", "3", "5"]
    },
    {
        "type": "select",
        "title": "Какое изображение прибора  соответствует условному обозначению «Переключатель электрических цепей измерения» ? Выберите единственно правильный ответ",
        "image": null,
        "component":"/templates_4/questions/question_1/slide_6.html",
        "answers": ["C"]
    },
    {
        "type": "radio",
        "title": "Какой прибор изображён на рисунке? Выберите единственно правильный ответ.",
        "image": null,
        "component":"/templates_4/questions/question_1/slide_7.html",
        "answers": ["C"]
    },
    {
        "type": "checkbox",
        "title": "Что определяют при создании функциональной схемы? Выберите все правильные ответы.",
        "image": null,
        "component":"/templates_4/questions/question_1/slide_8.html",
        "answers": ["A", "B", "C", "F"]
    },
    {
        "type": "radio",
        "title": "Что является основным документом, определяющим требования и порядок создания автоматизированной системы (АС), в соответствии с которым проводится разработка АС и ее приемка?Выберите единственно правильный ответ.",
        "image": null,
        "component":"/templates_4/questions/question_1/slide_9.html",
        "answers": ["A"]
    },
    {
        "type": "radio",
        "title": "Укажите в соответствии с каким ГОСТом определяются требования создания автоматизированной системы согласно техническому заданию.Выберите единственно правильный ответ.",
        "image": null,
        "component":"/templates_4/questions/question_1/slide_10.html",
        "answers": ["C"]
    },
    {
        "type": "radio",
        "title": "Разрешается ли снимать приборы, находящиеся под напряжением электрического тока? Выберите единственно правильный ответ.",
        "image": null,
        "component":"/templates_4/questions/question_1/slide_11.html",
        "answers": ["A"]
    },
    {
        "type": "radio",
        "title": "Могут ли быть допущены лица моложе 18 лет к работам по наладке приборов и средств автоматизации? Выберите единственно правильный ответ.",
        "image": null,
        "component":"/templates_4/questions/question_1/slide_12.html",
        "answers": ["B"]
    },
    {
        "type": "radio",
        "title": "Какие лица допускаются к работам по наладке приборов и средств автоматизации?Выберите единственно правильный ответ.",
        "image": null,
        "component":"/templates_4/questions/question_1/slide_13.html",
        "answers": ["F"]
    },
    {
        "type": "radio",
        "title": "Для чего предназначена автоматизированная система?Выберите единственно правильный ответ.",
        "image": null,
        "component":"/templates_4/questions/question_1/slide_14.html",
        "answers": ["C"]
    },
    {
        "type": "checkbox",
        "title": "Что рекомендуется при чтении схем автоматизации?Выберите все правильные ответы.",
        "image": null,
        "component":"/templates_4/questions/question_1/slide_14.html",
        "answers": ["B", "C", "D", "E"]
    }
]